pytumblr2/__init__.py
pytumblr2/helpers.py
pytumblr2/request.py
pytumblr2/format_conversion/__init__.py
pytumblr2/format_conversion/npf2html.py
PyTumblr2-0.2.4.dist-info/LICENSE
PyTumblr2-0.2.4.dist-info/METADATA
PyTumblr2-0.2.4.dist-info/NOTICE
PyTumblr2-0.2.4.dist-info/WHEEL
PyTumblr2-0.2.4.dist-info/top_level.txt
PyTumblr2-0.2.4.dist-info/RECORD
