Metadata-Version: 2.1
Name: PyTumblr2
Version: 0.2.4
Summary: A Python API v2 wrapper for Tumblr, updated for NPF compliance (and beyond!)
Home-page: https://github.com/nostalgebraist/pytumblr
Author: nostalgebraist
Author-email: nostalgebraist@gmail.com
License: Apache Software License 2.0
Keywords: pytumblr,pytumblr2,tumblr
Classifier: Development Status :: 4 - Beta
Classifier: Intended Audience :: Developers
Classifier: License :: OSI Approved :: Apache Software License
Classifier: Natural Language :: English
Classifier: Programming Language :: Python :: 3
Classifier: Programming Language :: Python :: 3.6
Classifier: Programming Language :: Python :: 3.7
Requires-Python: >=3.6
License-File: LICENSE
License-File: NOTICE
Requires-Dist: future
Requires-Dist: requests-oauthlib
